CHANGELOG.md
sortepy/__init__.py
sortepy/loterica.py
sortepy/script.py
sortepy/util.py
sorte.py-0.1.0.dev1.dist-info/entry_points.txt
sorte.py-0.1.0.dev1.dist-info/LICENSE
sorte.py-0.1.0.dev1.dist-info/WHEEL
sorte.py-0.1.0.dev1.dist-info/METADATA
sorte.py-0.1.0.dev1.dist-info/RECORD
