Metadata-Version: 2.1
Name: sorte.py
Version: 0.1.0.dev1
Summary: Geração e conferência de apostas de loterias.
Home-page: https://github.com/wagnerluis1982/sorte.py
License: GPL-3.0-only
Keywords: loteria,aposta,sorte.py
Author: Wagner Macedo
Author-email: wagnerluis1982@gmail.com
Requires-Python: >=3.8,<4.0
Classifier: Development Status :: 3 - Alpha
Classifier: Environment :: Console
Classifier: Intended Audience :: Developers
Classifier: Intended Audience :: End Users/Desktop
Classifier: License :: OSI Approved :: GNU General Public License v3 (GPLv3)
Classifier: Natural Language :: Portuguese (Brazilian)
Classifier: Programming Language :: Python :: 3
Classifier: Programming Language :: Python :: 3.10
Classifier: Programming Language :: Python :: 3.8
Classifier: Programming Language :: Python :: 3.9
Classifier: Topic :: Internet :: WWW/HTTP
Classifier: Topic :: Other/Nonlisted Topic
Project-URL: Repository, https://github.com/wagnerluis1982/sorte.py
